jsiter/__init__.py
jsiter-1.0.4.dist-info/LICENSE
jsiter-1.0.4.dist-info/METADATA
jsiter-1.0.4.dist-info/WHEEL
jsiter-1.0.4.dist-info/top_level.txt
jsiter-1.0.4.dist-info/RECORD
