Metadata-Version: 2.1
Name: jsiter
Version: 1.0.4
Summary: JavaScript flavor iterable
Home-page: https://github.com/HuJK/iterZ
Author: HuJK
Author-email: hu@hujk.eu.org
License: UNKNOWN
Platform: UNKNOWN
Classifier: Programming Language :: Python :: 3
Classifier: License :: OSI Approved :: MIT License
Classifier: Operating System :: OS Independent
Requires-Python: >=3.5
